memoiz/__about__.py
memoiz/__init__.py
memoiz/cache_exception.py
memoiz/memoiz.py
memoiz-4.0.8.dist-info/METADATA
memoiz-4.0.8.dist-info/WHEEL
memoiz-4.0.8.dist-info/licenses/LICENSE
memoiz-4.0.8.dist-info/RECORD
