Metadata-Version: 2.4
Name: memoiz
Version: 4.0.8
Summary: A decorator for adding memoization to functions and methods.
Project-URL: Homepage, https://github.com/faranalytics/memoiz.git
Project-URL: Bug Tracker, https://github.com/faranalytics/memoiz/issues
Author-email: Adam Patterson <adam@farar.net>
License-File: LICENSE
Classifier: License :: OSI Approved :: MIT License
Classifier: Operating System :: OS Independent
Classifier: Programming Language :: Python :: 3
Requires-Python: >=3.10
